Metadata-Version: 2.1
Name: tid-deploy-chk-model
Version: 0.0.7
Summary: Example regression model package from Train In Data.
Home-page: UNKNOWN
Author: VinayG
Author-email: gadikatlavinayteja@gmail.com
License: BSD-3
Platform: UNKNOWN
Classifier: License :: OSI Approved :: MIT License
Classifier: Programming Language :: Python
Classifier: Programming Language :: Python :: 3
Classifier: Programming Language :: Python :: 3.6
Classifier: Programming Language :: Python :: 3.7
Classifier: Programming Language :: Python :: 3.8
Classifier: Programming Language :: Python :: 3.9
Classifier: Programming Language :: Python :: Implementation :: CPython
Classifier: Programming Language :: Python :: Implementation :: PyPy
Requires-Python: >=3.6.0
Requires-Dist: numpy (<1.20.0,>=1.19.5)
Requires-Dist: pandas (<1.3.0,>=1.2.0)
Requires-Dist: pydantic (<1.9.0,>=1.8.1)
Requires-Dist: scikit-learn (<0.25.0,>=0.24.0)
Requires-Dist: strictyaml (<1.4.0,>=1.3.2)
Requires-Dist: ruamel.yaml (==0.16.12)
Requires-Dist: feature-engine (<1.1.3,>=1.1.2)
Requires-Dist: joblib (<1.0.0,>=0.14.1)
Requires-Dist: xgboost (==1.3.3)
